cyphermed/__init__.py
cyphermed/client.py
cyphermed/errors.py
cyphermed/py.typed
cyphermed/types.py
cyphermed/version.py
cyphermed/api/__init__.py
cyphermed/api/account/__init__.py
cyphermed/api/account/delete_account_picture.py
cyphermed/api/account/get_account_group_access.py
cyphermed/api/account/get_account_org_access.py
cyphermed/api/account/get_account_project_access.py
cyphermed/api/account/get_account_role_access.py
cyphermed/api/account/get_current_session_access.py
cyphermed/api/account/get_dashboard_config.py
cyphermed/api/account/send_sms_verification_code.py
cyphermed/api/account/set_account_picture.py
cyphermed/api/account/set_dashboard_config.py
cyphermed/api/account/verify_account_sms.py
cyphermed/api/auth/__init__.py
cyphermed/api/auth/add_sms_mfa.py
cyphermed/api/auth/add_software_mfa.py
cyphermed/api/auth/disable_sms_mfa.py
cyphermed/api/auth/disable_software_mfa.py
cyphermed/api/auth/enable_sms_mfa.py
cyphermed/api/auth/enable_software_mfa.py
cyphermed/api/auth/forgot_password.py
cyphermed/api/auth/get_mfa_secret_code.py
cyphermed/api/auth/login.py
cyphermed/api/auth/logout.py
cyphermed/api/auth/patch_mfa_settings.py
cyphermed/api/auth/remove_sms_mfa.py
cyphermed/api/auth/remove_software_mfa.py
cyphermed/api/auth/respond_to_challenge.py
cyphermed/api/auth/set_password.py
cyphermed/api/auth/trigger_forgot_password.py
cyphermed/api/data/__init__.py
cyphermed/api/data/bulk_json_data_request.py
cyphermed/api/data/delete_json_data.py
cyphermed/api/data/get_json_data.py
cyphermed/api/data/patch_json_data.py
cyphermed/api/data/post_json_data.py
cyphermed/api/data/put_json_data.py
cyphermed/api/devices/__init__.py
cyphermed/api/devices/close_all_device_tunnels.py
cyphermed/api/devices/close_device_tunnel_by_id.py
cyphermed/api/devices/create_device.py
cyphermed/api/devices/delete_device_by_id.py
cyphermed/api/devices/get_device_by_id.py
cyphermed/api/devices/get_device_tunnel_by_id.py
cyphermed/api/devices/get_device_tunnels.py
cyphermed-2.2.12.dist-info/LICENSE
cyphermed-2.2.12.dist-info/METADATA
cyphermed-2.2.12.dist-info/WHEEL
cyphermed-2.2.12.dist-info/top_level.txt
cyphermed-2.2.12.dist-info/RECORD
