Metadata-Version: 2.1
Name: cyphermed
Version: 2.2.12
Summary: Python SDK for the CypherMed Cloud plaform
Home-page: https://cyphermed.cloud
Author: CypherMed Cloud, LLC
Author-email: support@cyphermed.cloud
License: Apache-2.0
Project-URL: Documentation, https://py.cyphermed.cloud
License-File: LICENSE
Requires-Dist: attrs <24,>=23.2.0
Requires-Dist: httpx <1,>=0.25.2
Requires-Dist: python-dateutil <3,>=2.9.0.post0
